mlaa_experiment_module1/__init__.py
mlaa_experiment_module1/data_prepare.py
mlaa_experiment_module1/make_dataset_model.py
mlaa_experiment_module1/predict.py
mlaa_experiment_module1/training_model.py
mlaa_experiment_module1-0.1.1.dist-info/METADATA
mlaa_experiment_module1-0.1.1.dist-info/WHEEL
mlaa_experiment_module1-0.1.1.dist-info/RECORD
